translate4colors/README.MD
translate4colors/__init__.py
translate4colors/requirements.txt
translate4colors/thirdparty.json
translate4colors-0.12.dist-info/LICENSE.rst
translate4colors-0.12.dist-info/METADATA
translate4colors-0.12.dist-info/WHEEL
translate4colors-0.12.dist-info/top_level.txt
translate4colors-0.12.dist-info/RECORD
