Metadata-Version: 2.1
Name: translate4colors
Version: 0.12
Summary: automates text translation using Google Translate
Home-page: https://github.com/hansalemaos/translate4colors
Author: Johannes Fischer
Author-email: aulasparticularesdealemaosp@gmail.com
License: MIT
Keywords: google,translate
Classifier: Development Status :: 4 - Beta
Classifier: Programming Language :: Python :: 3 :: Only
Classifier: Programming Language :: Python :: 3.10
Classifier: Topic :: Software Development :: Libraries :: Python Modules
Classifier: Topic :: Utilities
License-File: LICENSE.rst
Requires-Dist: a-selenium2df
Requires-Dist: a-selenium-kill
Requires-Dist: kthread-sleep
Requires-Dist: retryloop
Requires-Dist: selenium
Requires-Dist: textwrapre
Requires-Dist: undetected-chromedriver
